llama_index/readers/kibela/__init__.py
llama_index/readers/kibela/base.py
llama_index_readers_kibela-0.4.1.dist-info/METADATA
llama_index_readers_kibela-0.4.1.dist-info/WHEEL
llama_index_readers_kibela-0.4.1.dist-info/licenses/LICENSE
llama_index_readers_kibela-0.4.1.dist-info/RECORD
