Metadata-Version: 2.4
Name: llama-index-readers-kibela
Version: 0.4.1
Summary: llama-index readers kibela integration
Author-email: Your Name <you@example.com>
Maintainer: higebu
License-Expression: MIT
License-File: LICENSE
Requires-Python: <4.0,>=3.9
Requires-Dist: gql<4,>=3.5.0
Requires-Dist: llama-index-core<0.15,>=0.13.0
